{
	"$schema": "http://schema.management.azure.com/schemas/2015-01-01/deploymentTemplate.json#",
	"contentVersion": "1.0.0.0",
	"parameters": {
		"factoryName": {
			"type": "string",
			"metadata": "Data Factory name",
			"defaultValue": "adf-course-rakeshm"
		},
		"AzureDL_Connection_accountKey": {
			"type": "secureString",
			"metadata": "Secure string for 'accountKey' of 'AzureDL_Connection'"
		},
		"AzureSqlDatabase_connection_password": {
			"type": "secureString",
			"metadata": "Secure string for 'password' of 'AzureSqlDatabase_connection'"
		},
		"AzureDL_Connection_properties_typeProperties_url": {
			"type": "string",
			"defaultValue": "https://storageadfrakesh1005.dfs.core.windows.net/"
		},
		"AzureSqlDatabase_connection_properties_typeProperties_server": {
			"type": "string",
			"defaultValue": "dfadvanceserver.database.windows.net"
		},
		"AzureSqlDatabase_connection_properties_typeProperties_database": {
			"type": "string",
			"defaultValue": "df-db"
		},
		"AzureSqlDatabase_connection_properties_typeProperties_userName": {
			"type": "string",
			"defaultValue": "rakesh"
		},
		"Git_connection_properties_typeProperties_url": {
			"type": "string",
			"defaultValue": "https://raw.githubusercontent.com"
		},
		"Rest_API_Connection_properties_typeProperties_url": {
			"type": "string",
			"defaultValue": " https://pokeapi.co/api/v2/pokemon"
		},
		"trigger2_properties_typeProperties_scope": {
			"type": "string",
			"defaultValue": "/subscriptions/a2688eea-3379-4c1a-a78c-d522a44487ef/resourceGroups/rg-adf-course/providers/Microsoft.Storage/storageAccounts/storageadfrakesh1005"
		},
		"trigger_storage_event_properties_typeProperties_scope": {
			"type": "string",
			"defaultValue": "/subscriptions/a2688eea-3379-4c1a-a78c-d522a44487ef/resourceGroups/rg-adf-course/providers/Microsoft.Storage/storageAccounts/storageadfrakesh1005"
		}
	},
	"variables": {
		"factoryId": "[concat('Microsoft.DataFactory/factories/', parameters('factoryName'))]"
	},
	"resources": [
		{
			"name": "[concat(parameters('factoryName'), '/demo')]",
			"type": "Microsoft.DataFactory/factories/pipelines",
			"apiVersion": "2018-06-01",
			"properties": {
				"activities": [
					{
						"name": "Wait1",
						"type": "Wait",
						"dependsOn": [],
						"userProperties": [],
						"typeProperties": {
							"waitTimeInSeconds": 10
						}
					}
				],
				"policy": {
					"elapsedTimeMetric": {}
				},
				"annotations": []
			},
			"dependsOn": []
		},
		{
			"name": "[concat(parameters('factoryName'), '/AzureDL_Connection')]",
			"type": "Microsoft.DataFactory/factories/linkedServices",
			"apiVersion": "2018-06-01",
			"properties": {
				"annotations": [],
				"type": "AzureBlobFS",
				"typeProperties": {
					"url": "[parameters('AzureDL_Connection_properties_typeProperties_url')]",
					"accountKey": {
						"type": "SecureString",
						"value": "[parameters('AzureDL_Connection_accountKey')]"
					}
				}
			},
			"dependsOn": []
		},
		{
			"name": "[concat(parameters('factoryName'), '/AzureSqlDatabase_connection')]",
			"type": "Microsoft.DataFactory/factories/linkedServices",
			"apiVersion": "2018-06-01",
			"properties": {
				"annotations": [],
				"type": "AzureSqlDatabase",
				"typeProperties": {
					"server": "[parameters('AzureSqlDatabase_connection_properties_typeProperties_server')]",
					"database": "[parameters('AzureSqlDatabase_connection_properties_typeProperties_database')]",
					"encrypt": "optional",
					"trustServerCertificate": false,
					"authenticationType": "SQL",
					"userName": "[parameters('AzureSqlDatabase_connection_properties_typeProperties_userName')]",
					"password": {
						"type": "SecureString",
						"value": "[parameters('AzureSqlDatabase_connection_password')]"
					}
				}
			},
			"dependsOn": []
		},
		{
			"name": "[concat(parameters('factoryName'), '/Git_connection')]",
			"type": "Microsoft.DataFactory/factories/linkedServices",
			"apiVersion": "2018-06-01",
			"properties": {
				"annotations": [],
				"type": "HttpServer",
				"typeProperties": {
					"url": "[parameters('Git_connection_properties_typeProperties_url')]",
					"enableServerCertificateValidation": true,
					"authenticationType": "Anonymous"
				}
			},
			"dependsOn": []
		},
		{
			"name": "[concat(parameters('factoryName'), '/Rest_API_Connection')]",
			"type": "Microsoft.DataFactory/factories/linkedServices",
			"apiVersion": "2018-06-01",
			"properties": {
				"annotations": [],
				"type": "RestService",
				"typeProperties": {
					"url": "[parameters('Rest_API_Connection_properties_typeProperties_url')]",
					"enableServerCertificateValidation": true,
					"authenticationType": "Anonymous"
				}
			},
			"dependsOn": []
		},
		{
			"name": "[concat(parameters('factoryName'), '/trigger1')]",
			"type": "Microsoft.DataFactory/factories/triggers",
			"apiVersion": "2018-06-01",
			"properties": {
				"annotations": [],
				"runtimeState": "Stopped",
				"pipelines": [],
				"type": "ScheduleTrigger",
				"typeProperties": {
					"recurrence": {
						"frequency": "Minute",
						"interval": 15,
						"startTime": "2026-06-09T16:02:00",
						"endTime": "2026-06-09T16:10:00",
						"timeZone": "India Standard Time"
					}
				}
			},
			"dependsOn": []
		},
		{
			"name": "[concat(parameters('factoryName'), '/trigger2')]",
			"type": "Microsoft.DataFactory/factories/triggers",
			"apiVersion": "2018-06-01",
			"properties": {
				"annotations": [],
				"runtimeState": "Stopped",
				"pipelines": [],
				"type": "BlobEventsTrigger",
				"typeProperties": {
					"blobPathBeginsWith": "/source/blobs/csvfiles/employees.csv",
					"ignoreEmptyBlobs": true,
					"scope": "[parameters('trigger2_properties_typeProperties_scope')]",
					"events": [
						"Microsoft.Storage.BlobCreated"
					]
				}
			},
			"dependsOn": []
		},
		{
			"name": "[concat(parameters('factoryName'), '/trigger_storage_event')]",
			"type": "Microsoft.DataFactory/factories/triggers",
			"apiVersion": "2018-06-01",
			"properties": {
				"annotations": [],
				"runtimeState": "Stopped",
				"pipelines": [],
				"type": "BlobEventsTrigger",
				"typeProperties": {
					"blobPathBeginsWith": "/source/blobs/csvfiles/employees.csv",
					"ignoreEmptyBlobs": true,
					"scope": "[parameters('trigger_storage_event_properties_typeProperties_scope')]",
					"events": [
						"Microsoft.Storage.BlobCreated"
					]
				}
			},
			"dependsOn": []
		},
		{
			"name": "[concat(parameters('factoryName'), '/API_to_Json')]",
			"type": "Microsoft.DataFactory/factories/datasets",
			"apiVersion": "2018-06-01",
			"properties": {
				"linkedServiceName": {
					"referenceName": "AzureDL_Connection",
					"type": "LinkedServiceReference"
				},
				"annotations": [],
				"type": "Json",
				"typeProperties": {
					"location": {
						"type": "AzureBlobFSLocation",
						"fileName": "pokemon.json",
						"folderPath": "API_data",
						"fileSystem": "target"
					}
				},
				"schema": {}
			},
			"dependsOn": [
				"[concat(variables('factoryId'), '/linkedServices/AzureDL_Connection')]"
			]
		},
		{
			"name": "[concat(parameters('factoryName'), '/Dynamic_dataset')]",
			"type": "Microsoft.DataFactory/factories/datasets",
			"apiVersion": "2018-06-01",
			"properties": {
				"linkedServiceName": {
					"referenceName": "AzureDL_Connection",
					"type": "LinkedServiceReference"
				},
				"parameters": {
					"container": {
						"type": "string"
					},
					"folder": {
						"type": "string"
					},
					"file_name": {
						"type": "string"
					}
				},
				"annotations": [],
				"type": "DelimitedText",
				"typeProperties": {
					"location": {
						"type": "AzureBlobFSLocation",
						"fileName": {
							"value": "@dataset().file_name",
							"type": "Expression"
						},
						"folderPath": {
							"value": "@dataset().folder",
							"type": "Expression"
						},
						"fileSystem": {
							"value": "@dataset().container",
							"type": "Expression"
						}
					},
					"columnDelimiter": ",",
					"escapeChar": "\\",
					"firstRowAsHeader": true,
					"quoteChar": "\""
				},
				"schema": []
			},
			"dependsOn": [
				"[concat(variables('factoryId'), '/linkedServices/AzureDL_Connection')]"
			]
		},
		{
			"name": "[concat(parameters('factoryName'), '/Rest_API_source')]",
			"type": "Microsoft.DataFactory/factories/datasets",
			"apiVersion": "2018-06-01",
			"properties": {
				"linkedServiceName": {
					"referenceName": "Rest_API_Connection",
					"type": "LinkedServiceReference"
				},
				"annotations": [],
				"type": "RestResource",
				"typeProperties": {
					"relativeUrl": {
						"value": "?offset={offset}",
						"type": "Expression"
					}
				},
				"schema": []
			},
			"dependsOn": [
				"[concat(variables('factoryId'), '/linkedServices/Rest_API_Connection')]"
			]
		},
		{
			"name": "[concat(parameters('factoryName'), '/cdc_timestamp')]",
			"type": "Microsoft.DataFactory/factories/datasets",
			"apiVersion": "2018-06-01",
			"properties": {
				"linkedServiceName": {
					"referenceName": "AzureDL_Connection",
					"type": "LinkedServiceReference"
				},
				"annotations": [],
				"type": "Json",
				"typeProperties": {
					"location": {
						"type": "AzureBlobFSLocation",
						"fileName": "cdc.json",
						"folderPath": "monitor",
						"fileSystem": "source"
					}
				},
				"schema": {}
			},
			"dependsOn": [
				"[concat(variables('factoryId'), '/linkedServices/AzureDL_Connection')]"
			]
		},
		{
			"name": "[concat(parameters('factoryName'), '/csv_netflix_source')]",
			"type": "Microsoft.DataFactory/factories/datasets",
			"apiVersion": "2018-06-01",
			"properties": {
				"linkedServiceName": {
					"referenceName": "AzureDL_Connection",
					"type": "LinkedServiceReference"
				},
				"parameters": {
					"file_name": {
						"type": "string"
					}
				},
				"annotations": [],
				"type": "DelimitedText",
				"typeProperties": {
					"location": {
						"type": "AzureBlobFSLocation",
						"fileName": {
							"value": "@dataset().file_name",
							"type": "Expression"
						},
						"folderPath": "csv_files",
						"fileSystem": "target"
					},
					"columnDelimiter": ",",
					"escapeChar": "\\",
					"firstRowAsHeader": true,
					"quoteChar": "\""
				},
				"schema": []
			},
			"dependsOn": [
				"[concat(variables('factoryId'), '/linkedServices/AzureDL_Connection')]"
			]
		},
		{
			"name": "[concat(parameters('factoryName'), '/csv_source')]",
			"type": "Microsoft.DataFactory/factories/datasets",
			"apiVersion": "2018-06-01",
			"properties": {
				"linkedServiceName": {
					"referenceName": "AzureDL_Connection",
					"type": "LinkedServiceReference"
				},
				"annotations": [],
				"type": "DelimitedText",
				"typeProperties": {
					"location": {
						"type": "AzureBlobFSLocation",
						"fileName": "Fact_Sales_1 (1).csv",
						"folderPath": "csvfiles",
						"fileSystem": "source"
					},
					"columnDelimiter": ",",
					"escapeChar": "\\",
					"firstRowAsHeader": true,
					"quoteChar": "\""
				},
				"schema": []
			},
			"dependsOn": [
				"[concat(variables('factoryId'), '/linkedServices/AzureDL_Connection')]"
			]
		},
		{
			"name": "[concat(parameters('factoryName'), '/csv_to_Parquet_target')]",
			"type": "Microsoft.DataFactory/factories/datasets",
			"apiVersion": "2018-06-01",
			"properties": {
				"linkedServiceName": {
					"referenceName": "AzureDL_Connection",
					"type": "LinkedServiceReference"
				},
				"annotations": [],
				"type": "Parquet",
				"typeProperties": {
					"location": {
						"type": "AzureBlobFSLocation",
						"folderPath": "parquet_files",
						"fileSystem": "target"
					},
					"compressionCodec": "snappy"
				},
				"schema": []
			},
			"dependsOn": [
				"[concat(variables('factoryId'), '/linkedServices/AzureDL_Connection')]"
			]
		},
		{
			"name": "[concat(parameters('factoryName'), '/dataset_customer_csv')]",
			"type": "Microsoft.DataFactory/factories/datasets",
			"apiVersion": "2018-06-01",
			"properties": {
				"linkedServiceName": {
					"referenceName": "AzureDL_Connection",
					"type": "LinkedServiceReference"
				},
				"parameters": {
					"p_conatiner": {
						"type": "string"
					},
					"p_folder": {
						"type": "string"
					},
					"p_filename": {
						"type": "string"
					}
				},
				"annotations": [],
				"type": "DelimitedText",
				"typeProperties": {
					"location": {
						"type": "AzureBlobFSLocation",
						"fileName": {
							"value": "@dataset().p_filename",
							"type": "Expression"
						},
						"folderPath": {
							"value": "@dataset().p_folder",
							"type": "Expression"
						},
						"fileSystem": {
							"value": "@dataset().p_conatiner",
							"type": "Expression"
						}
					},
					"columnDelimiter": ",",
					"escapeChar": "\\",
					"firstRowAsHeader": true,
					"quoteChar": "\""
				},
				"schema": []
			},
			"dependsOn": [
				"[concat(variables('factoryId'), '/linkedServices/AzureDL_Connection')]"
			]
		},
		{
			"name": "[concat(parameters('factoryName'), '/emp_tgt')]",
			"type": "Microsoft.DataFactory/factories/datasets",
			"apiVersion": "2018-06-01",
			"properties": {
				"linkedServiceName": {
					"referenceName": "AzureDL_Connection",
					"type": "LinkedServiceReference"
				},
				"annotations": [],
				"type": "DelimitedText",
				"typeProperties": {
					"location": {
						"type": "AzureBlobFSLocation",
						"folderPath": "csv_files",
						"fileSystem": "target"
					},
					"columnDelimiter": ",",
					"escapeChar": "\\",
					"firstRowAsHeader": true,
					"quoteChar": "\""
				},
				"schema": []
			},
			"dependsOn": [
				"[concat(variables('factoryId'), '/linkedServices/AzureDL_Connection')]"
			]
		},
		{
			"name": "[concat(parameters('factoryName'), '/emp_tgt1')]",
			"type": "Microsoft.DataFactory/factories/datasets",
			"apiVersion": "2018-06-01",
			"properties": {
				"linkedServiceName": {
					"referenceName": "AzureDL_Connection",
					"type": "LinkedServiceReference"
				},
				"annotations": [],
				"type": "DelimitedText",
				"typeProperties": {
					"location": {
						"type": "AzureBlobFSLocation",
						"fileName": "emp_tgt.csv",
						"folderPath": "csv_files",
						"fileSystem": "target"
					},
					"columnDelimiter": ",",
					"escapeChar": "\\",
					"firstRowAsHeader": true,
					"quoteChar": "\""
				},
				"schema": []
			},
			"dependsOn": [
				"[concat(variables('factoryId'), '/linkedServices/AzureDL_Connection')]"
			]
		},
		{
			"name": "[concat(parameters('factoryName'), '/emp_tgt_2')]",
			"type": "Microsoft.DataFactory/factories/datasets",
			"apiVersion": "2018-06-01",
			"properties": {
				"linkedServiceName": {
					"referenceName": "AzureDL_Connection",
					"type": "LinkedServiceReference"
				},
				"annotations": [],
				"type": "DelimitedText",
				"typeProperties": {
					"location": {
						"type": "AzureBlobFSLocation",
						"folderPath": "csv_files",
						"fileSystem": "target"
					},
					"columnDelimiter": ",",
					"escapeChar": "\\",
					"firstRowAsHeader": true,
					"quoteChar": "\""
				},
				"schema": []
			},
			"dependsOn": [
				"[concat(variables('factoryId'), '/linkedServices/AzureDL_Connection')]"
			]
		},
		{
			"name": "[concat(parameters('factoryName'), '/employee')]",
			"type": "Microsoft.DataFactory/factories/datasets",
			"apiVersion": "2018-06-01",
			"properties": {
				"linkedServiceName": {
					"referenceName": "AzureDL_Connection",
					"type": "LinkedServiceReference"
				},
				"annotations": [],
				"type": "DelimitedText",
				"typeProperties": {
					"location": {
						"type": "AzureBlobFSLocation",
						"fileName": "employees.csv",
						"folderPath": "csvfiles",
						"fileSystem": "source"
					},
					"columnDelimiter": ",",
					"escapeChar": "\\",
					"firstRowAsHeader": true,
					"quoteChar": "\""
				},
				"schema": []
			},
			"dependsOn": [
				"[concat(variables('factoryId'), '/linkedServices/AzureDL_Connection')]"
			]
		}
	]
}